p_tree/__init__.py
p_tree/dbox.py
p_tree/run.py
p_tree/utilities.py
p_tree-0.1.16.dist-info/DESCRIPTION.rst
p_tree-0.1.16.dist-info/METADATA
p_tree-0.1.16.dist-info/RECORD
p_tree-0.1.16.dist-info/WHEEL
p_tree-0.1.16.dist-info/metadata.json
p_tree-0.1.16.dist-info/top_level.txt
